{
  "number": 1,
  "player": {
    "x": 5.706754,
    "y": 11.807249
  },
  "goal": {
    "x": 0.0,
    "y": 0.0
  },
  "enemies": {
    "(11.075003,18.455996)": [
      {
        "x": 443.00012,
        "y": 738.2398
      },
      {
        "x": 785.78,
        "y": 742.1799
      },
      {
        "x": 1171.8998,
        "y": 657.47
      },
      {
        "x": 1207.3597,
        "y": 269.3801
      },
      {
        "x": 1043.8499,
        "y": -18.239748
      },
      {
        "x": 703.0399,
        "y": -95.06974
      },
      {
        "x": 192.81021,
        "y": -37.939762
      },
      {
        "x": 37.1803,
        "y": 210.28012
      },
      {
        "x": 137.65022,
        "y": 537.3
      },
      {
        "x": 435.1201,
        "y": 728.38983
      }
    ]
  },
  "lilypads": [
    {
      "x": 11.375,
      "y": 11.450002
    },
    {
      "x": 21.959248,
      "y": 14.26975
    },
    {
      "x": 25.209743,
      "y": 7.9165015
    },
    {
      "x": 16.591,
      "y": 2.1050043
    }
  ],
  "lotuses": [
    {
      "x": 8.563253,
      "y": 3.9272532
    },
    {
      "x": 5.411255,
      "y": 7.9657507
    },
    {
      "x": 17.379002,
      "y": 8.359751
    }
  ],
  "walls": [
    [
      -2.6657429,
      22.346745,
      -2.3209918,
      -3.8049932,
      -7.29524,
      -4.691492,
      -7.787739,
      22.592995,
      -2.616492,
      22.642246
    ],
    [
      -2.3209918,
      22.839245,
      32.10474,
      22.100494,
      31.710745,
      25.006245,
      -2.616492,
      24.415245,
      -2.5672429,
      23.134747
    ],
    [
      32.400246,
      22.198996,
      32.400246,
      -5.873492,
      37.86699,
      -6.759992,
      35.79849,
      22.346745,
      32.74499,
      22.100494
    ],
    [
      32.00624,
      -4.986993,
      -1.1389924,
      -3.5094929,
      -2.5179906,
      -7.7942405,
      31.661495,
      -8.040491,
      32.00624,
      -5.3317423
    ]
  ]
}
Controllers: removed manager for application, 0 managers active
